ibl_pipeline/__init__.py
ibl_pipeline/acquisition.py
ibl_pipeline/action.py
ibl_pipeline/behavior.py
ibl_pipeline/common.py
ibl_pipeline/data.py
ibl_pipeline/ephys.py
ibl_pipeline/histology.py
ibl_pipeline/public.py
ibl_pipeline/qc.py
ibl_pipeline/reference.py
ibl_pipeline/subject.py
ibl_pipeline/update.py
ibl_pipeline/analyses/__init__.py
ibl_pipeline/analyses/analysis_utils.py
ibl_pipeline/analyses/behavior.py
ibl_pipeline/analyses/end_session_criteria.py
ibl_pipeline/analyses/ephys.py
ibl_pipeline/group_shared/__init__.py
ibl_pipeline/group_shared/wheel.py
ibl_pipeline/ingest/__init__.py
ibl_pipeline/ingest/acquisition.py
ibl_pipeline/ingest/action.py
ibl_pipeline/ingest/alyxraw.py
ibl_pipeline/ingest/common.py
ibl_pipeline/ingest/data.py
ibl_pipeline/ingest/ephys.py
ibl_pipeline/ingest/histology.py
ibl_pipeline/ingest/ingest_utils.py
ibl_pipeline/ingest/job.py
ibl_pipeline/ingest/qc.py
ibl_pipeline/ingest/reference.py
ibl_pipeline/ingest/subject.py
ibl_pipeline/plotting/__init__.py
ibl_pipeline/plotting/behavior.py
ibl_pipeline/plotting/ephys.py
ibl_pipeline/plotting/ephys_plotting.py
ibl_pipeline/plotting/figure_model.py
ibl_pipeline/plotting/plotting_utils_behavior.py
ibl_pipeline/plotting/plotting_utils_ephys.py
ibl_pipeline/plotting/utils.py
ibl_pipeline/process/__init__.py
ibl_pipeline/process/autoprocess.py
ibl_pipeline/process/create_ingest_task.py
ibl_pipeline/process/delete_update_entries.py
ibl_pipeline/process/ingest_alyx_raw.py
ibl_pipeline/process/ingest_membership.py
ibl_pipeline/process/ingest_real.py
ibl_pipeline/process/ingest_shadow.py
ibl_pipeline/process/populate_behavior.py
ibl_pipeline/process/populate_ephys.py
ibl_pipeline/process/process_histology.py
ibl_pipeline/process/process_qc.py
ibl_pipeline/process/update_utils.py
ibl_pipeline/utils/__init__.py
ibl_pipeline/utils/atlas.py
ibl_pipeline/utils/delete_unused_external.py
ibl_pipeline/utils/dependent_tables.py
ibl_pipeline/utils/dj_alter_table.py
ibl_pipeline/utils/dj_compare_table.py
ibl_pipeline-0.2.4.dist-info/METADATA
ibl_pipeline-0.2.4.dist-info/WHEEL
ibl_pipeline-0.2.4.dist-info/top_level.txt
ibl_pipeline-0.2.4.dist-info/RECORD
