Metadata-Version: 2.1
Name: ibl-pipeline
Version: 0.2.4
Summary: Datajoint schemas for IBL
Home-page: UNKNOWN
Author: Vathes
Author-email: support@vathes.com
License: UNKNOWN
Platform: UNKNOWN
Requires-Dist: datajoint (~=0.12)
Requires-Dist: ibllib (>=1.4.11)
Requires-Dist: numpy (>=1.18.1)
Requires-Dist: seaborn (>=0.10.0)
Requires-Dist: globus-sdk
Requires-Dist: boto3
Requires-Dist: colorlover
Requires-Dist: scikits.bootstrap
Requires-Dist: statsmodels (>=0.10.1)
Requires-Dist: plotly (>=4.1.0)
